putplace_server/__init__.py
putplace_server/auth.py
putplace_server/cleanup_tasks.py
putplace_server/config.py
putplace_server/database.py
putplace_server/dependencies.py
putplace_server/email_service.py
putplace_server/email_tokens.py
putplace_server/main.py
putplace_server/models.py
putplace_server/ppserver.py
putplace_server/storage.py
putplace_server/templates.py
putplace_server/user_auth.py
putplace_server/version.py
putplace_server/routers/__init__.py
putplace_server/routers/admin.py
putplace_server/routers/api_keys.py
putplace_server/routers/files.py
putplace_server/routers/pages.py
putplace_server/routers/uploads.py
putplace_server/routers/users.py
putplace_server/scripts/README_send_ses_email.md
putplace_server/scripts/__init__.py
putplace_server/scripts/atlas_cluster_control.py
putplace_server/scripts/create_api_key.py
putplace_server/scripts/deploy_digitalocean.py
putplace_server/scripts/deploy_digitalocean_old.py
putplace_server/scripts/pp_manage_users.py
putplace_server/scripts/purge_data.py
putplace_server/scripts/putplace_configure.py
putplace_server/scripts/send_ses_email.py
putplace_server/scripts/setup_apprunner_fixed_ip.py
putplace_server/scripts/setup_aws_iam_users.py
putplace_server/scripts/toggle_registration.py
putplace_server/scripts/update_apprunner_vpc.py
putplace_server/scripts/update_deployment.py
putplace_server/static/README.md
putplace_server/static/css/.gitkeep
putplace_server/static/images/.gitkeep
putplace_server/static/images/LOGO_USAGE.md
putplace_server/static/images/favicon.svg
putplace_server/static/images/putplace-logo.svg
putplace_server/static/js/.gitkeep
putplace_server-0.10.2.dist-info/METADATA
putplace_server-0.10.2.dist-info/WHEEL
putplace_server-0.10.2.dist-info/entry_points.txt
putplace_server-0.10.2.dist-info/RECORD
