Metadata-Version: 2.4
Name: putplace-server
Version: 0.10.2
Summary: PutPlace FastAPI server for file metadata storage
License: Apache-2.0
Classifier: Development Status :: 4 - Beta
Classifier: Framework :: FastAPI
Classifier: Intended Audience :: Developers
Classifier: Intended Audience :: System Administrators
Classifier: License :: OSI Approved :: Apache Software License
Classifier: Programming Language :: Python :: 3
Classifier: Programming Language :: Python :: 3.10
Classifier: Programming Language :: Python :: 3.11
Classifier: Programming Language :: Python :: 3.12
Classifier: Programming Language :: Python :: 3.13
Classifier: Programming Language :: Python :: 3.14
Classifier: Topic :: System :: Archiving
Classifier: Topic :: System :: Filesystems
Classifier: Topic :: System :: Systems Administration
Requires-Python: >=3.10
Requires-Dist: aioboto3>=12.0.0
Requires-Dist: argon2-cffi>=23.1.0
Requires-Dist: authlib>=1.3.0
Requires-Dist: boto3>=1.34.0
Requires-Dist: certifi>=2023.0.0
Requires-Dist: configargparse>=1.7.0
Requires-Dist: fastapi>=0.110.0
Requires-Dist: google-auth>=2.27.0
Requires-Dist: httpx>=0.26.0
Requires-Dist: invoke>=2.2.1
Requires-Dist: pydantic-settings>=2.1.0
Requires-Dist: pydantic>=2.6.0
Requires-Dist: pymongo>=4.10.0
Requires-Dist: python-dotenv>=1.0.0
Requires-Dist: python-jose[cryptography]>=3.3.0
Requires-Dist: python-multipart>=0.0.6
Requires-Dist: rich>=13.7.0
Requires-Dist: tomli-w>=1.0.0
Requires-Dist: tomli>=2.0.0; python_version < '3.11'
Requires-Dist: uvicorn[standard]>=0.27.0
Provides-Extra: dev
Requires-Dist: invoke>=2.2.0; extra == 'dev'
Requires-Dist: mypy>=1.8.0; extra == 'dev'
Requires-Dist: pytest-asyncio>=0.23.0; extra == 'dev'
Requires-Dist: pytest-cov>=4.1.0; extra == 'dev'
Requires-Dist: pytest-xdist>=3.5.0; extra == 'dev'
Requires-Dist: pytest>=8.0.0; extra == 'dev'
Requires-Dist: ruff>=0.3.0; extra == 'dev'
Requires-Dist: twine>=5.0.0; extra == 'dev'
